{
  "_format": "hh-sol-cache-2",
  "files": {
    "/Users/ghazalehkeshavarz/Documents/study/Barcelona/FederatedNaiveBayesZKP/contracts/BJJ.sol": {
      "lastModificationDate": 1696840959166,
      "contentHash": "86832fcca0a4fbd3e4e5f56124443166",
      "sourceName": "contracts/BJJ.sol",
      "solcConfig": {
        "version": "0.8.6",
        "settings": {
          "optimizer": {
            "enabled": false,
            "runs": 200
          },
          "outputSelection": {
            "*": {
              "*": [
                "abi",
                "evm.bytecode",
                "evm.deployedBytecode",
                "evm.methodIdentifiers",
                "metadata"
              ],
              "": [
                "ast"
              ]
            }
          }
        }
      },
      "imports": [],
      "versionPragmas": [
        ">=0.4.17 <0.8.7"
      ],
      "artifacts": [
        "BJJ"
      ]
    },
    "/Users/ghazalehkeshavarz/Documents/study/Barcelona/FederatedNaiveBayesZKP/contracts/FLSC.sol": {
      "lastModificationDate": 1697797727118,
      "contentHash": "0952c756ad6f0e36f994eaa6c021c7bd",
      "sourceName": "contracts/FLSC.sol",
      "solcConfig": {
        "version": "0.8.6",
        "settings": {
          "optimizer": {
            "enabled": false,
            "runs": 200
          },
          "outputSelection": {
            "*": {
              "*": [
                "abi",
                "evm.bytecode",
                "evm.deployedBytecode",
                "evm.methodIdentifiers",
                "metadata"
              ],
              "": [
                "ast"
              ]
            }
          }
        }
      },
      "imports": [
        "./BJJ.sol",
        "./verifier.sol"
      ],
      "versionPragmas": [
        ">=0.8.0 <0.8.7"
      ],
      "artifacts": [
        "FLSC"
      ]
    },
    "/Users/ghazalehkeshavarz/Documents/study/Barcelona/FederatedNaiveBayesZKP/contracts/verifier.sol": {
      "lastModificationDate": 1697797727129,
      "contentHash": "222da80f1e258de2f29ded8c0c27aa10",
      "sourceName": "contracts/verifier.sol",
      "solcConfig": {
        "version": "0.8.6",
        "settings": {
          "optimizer": {
            "enabled": false,
            "runs": 200
          },
          "outputSelection": {
            "*": {
              "*": [
                "abi",
                "evm.bytecode",
                "evm.deployedBytecode",
                "evm.methodIdentifiers",
                "metadata"
              ],
              "": [
                "ast"
              ]
            }
          }
        }
      },
      "imports": [],
      "versionPragmas": [
        "^0.8.0"
      ],
      "artifacts": [
        "DVSC",
        "MVSC",
        "Pairing"
      ]
    },
    "/Users/ghazalehkeshavarz/Documents/study/Barcelona/FederatedNaiveBayesZKP/contracts/DVSC.sol": {
      "lastModificationDate": 1697797727101,
      "contentHash": "9532499f70a9658c8816b2186d9aade8",
      "sourceName": "contracts/DVSC.sol",
      "solcConfig": {
        "version": "0.8.6",
        "settings": {
          "optimizer": {
            "enabled": false,
            "runs": 200
          },
          "outputSelection": {
            "*": {
              "*": [
                "abi",
                "evm.bytecode",
                "evm.deployedBytecode",
                "evm.methodIdentifiers",
                "metadata"
              ],
              "": [
                "ast"
              ]
            }
          }
        }
      },
      "imports": [],
      "versionPragmas": [
        "^0.8.0"
      ],
      "artifacts": [
        "Pairing",
        "Verifier"
      ]
    },
    "/Users/ghazalehkeshavarz/Documents/study/Barcelona/FederatedNaiveBayesZKP/contracts/MVSC.sol": {
      "lastModificationDate": 1697797727067,
      "contentHash": "b448062d44a7ee3bea299c05bd19b488",
      "sourceName": "contracts/MVSC.sol",
      "solcConfig": {
        "version": "0.8.6",
        "settings": {
          "optimizer": {
            "enabled": false,
            "runs": 200
          },
          "outputSelection": {
            "*": {
              "*": [
                "abi",
                "evm.bytecode",
                "evm.deployedBytecode",
                "evm.methodIdentifiers",
                "metadata"
              ],
              "": [
                "ast"
              ]
            }
          }
        }
      },
      "imports": [],
      "versionPragmas": [
        "^0.8.0"
      ],
      "artifacts": [
        "Pairing",
        "Verifier"
      ]
    },
    "/Users/ghazalehkeshavarz/Documents/study/Barcelona/repocheck/FederatedNaiveBayesZKP/contracts/BJJ.sol": {
      "lastModificationDate": 1698767568321,
      "contentHash": "86832fcca0a4fbd3e4e5f56124443166",
      "sourceName": "contracts/BJJ.sol",
      "solcConfig": {
        "version": "0.8.6",
        "settings": {
          "optimizer": {
            "enabled": false,
            "runs": 200
          },
          "outputSelection": {
            "*": {
              "*": [
                "abi",
                "evm.bytecode",
                "evm.deployedBytecode",
                "evm.methodIdentifiers",
                "metadata"
              ],
              "": [
                "ast"
              ]
            }
          }
        }
      },
      "imports": [],
      "versionPragmas": [
        ">=0.4.17 <0.8.7"
      ],
      "artifacts": [
        "BJJ"
      ]
    },
    "/Users/ghazalehkeshavarz/Documents/study/Barcelona/repocheck/FederatedNaiveBayesZKP/contracts/FLSC.sol": {
      "lastModificationDate": 1699260587498,
      "contentHash": "0952c756ad6f0e36f994eaa6c021c7bd",
      "sourceName": "contracts/FLSC.sol",
      "solcConfig": {
        "version": "0.8.6",
        "settings": {
          "optimizer": {
            "enabled": false,
            "runs": 200
          },
          "outputSelection": {
            "*": {
              "*": [
                "abi",
                "evm.bytecode",
                "evm.deployedBytecode",
                "evm.methodIdentifiers",
                "metadata"
              ],
              "": [
                "ast"
              ]
            }
          }
        }
      },
      "imports": [
        "./BJJ.sol",
        "./verifier.sol"
      ],
      "versionPragmas": [
        ">=0.8.0 <0.8.7"
      ],
      "artifacts": [
        "FLSC"
      ]
    },
    "/Users/ghazalehkeshavarz/Documents/study/Barcelona/repocheck/FederatedNaiveBayesZKP/contracts/verifier.sol": {
      "lastModificationDate": 1699260587508,
      "contentHash": "f2df4d33ff8a97c0669bc69fa38e92fe",
      "sourceName": "contracts/verifier.sol",
      "solcConfig": {
        "version": "0.8.6",
        "settings": {
          "optimizer": {
            "enabled": false,
            "runs": 200
          },
          "outputSelection": {
            "*": {
              "*": [
                "abi",
                "evm.bytecode",
                "evm.deployedBytecode",
                "evm.methodIdentifiers",
                "metadata"
              ],
              "": [
                "ast"
              ]
            }
          }
        }
      },
      "imports": [],
      "versionPragmas": [
        "^0.8.0"
      ],
      "artifacts": [
        "DVSC",
        "MVSC",
        "Pairing"
      ]
    },
    "/Users/ghazalehkeshavarz/Documents/study/Barcelona/repocheck/FederatedNaiveBayesZKP/contracts/DVSC.sol": {
      "lastModificationDate": 1699260587485,
      "contentHash": "38024aa71f5bf8661377b74af744bb07",
      "sourceName": "contracts/DVSC.sol",
      "solcConfig": {
        "version": "0.8.6",
        "settings": {
          "optimizer": {
            "enabled": false,
            "runs": 200
          },
          "outputSelection": {
            "*": {
              "*": [
                "abi",
                "evm.bytecode",
                "evm.deployedBytecode",
                "evm.methodIdentifiers",
                "metadata"
              ],
              "": [
                "ast"
              ]
            }
          }
        }
      },
      "imports": [],
      "versionPragmas": [
        "^0.8.0"
      ],
      "artifacts": [
        "Pairing",
        "Verifier"
      ]
    },
    "/Users/ghazalehkeshavarz/Documents/study/Barcelona/repocheck/FederatedNaiveBayesZKP/contracts/MVSC.sol": {
      "lastModificationDate": 1699260560340,
      "contentHash": "e92658745fb179a0f22e901745297e29",
      "sourceName": "contracts/MVSC.sol",
      "solcConfig": {
        "version": "0.8.6",
        "settings": {
          "optimizer": {
            "enabled": false,
            "runs": 200
          },
          "outputSelection": {
            "*": {
              "*": [
                "abi",
                "evm.bytecode",
                "evm.deployedBytecode",
                "evm.methodIdentifiers",
                "metadata"
              ],
              "": [
                "ast"
              ]
            }
          }
        }
      },
      "imports": [],
      "versionPragmas": [
        "^0.8.0"
      ],
      "artifacts": [
        "Pairing",
        "Verifier"
      ]
    }
  }
}
